README.md
setup.py
pylimit/__init__.py
pylimit/check.py
pylimit/const.py
pylimit/const_error.py
pylimit/limit_error.py
pylimit/list_limit.py
pylimit/tuple_limit.py
pylimit/type_limit.py
pylimit/value_range.py
pylimit2.egg-info/PKG-INFO
pylimit2.egg-info/SOURCES.txt
pylimit2.egg-info/dependency_links.txt
pylimit2.egg-info/top_level.txt