Metadata-Version: 1.1
Name: pylimit2
Version: 0.1.0
Summary: 作为pylimit的升级版，支持py3.5+，使用更方便
Home-page: https://github.com/hey-bruce/pylimit2
Author: BBruceyuan
Author-email: bruceyuan123@gmail.com
License: UNKNOWN
Platform: UNKNOWN
Classifier: Development Status :: 3 - Alpha
Classifier: Intended Audience :: Developers
Classifier: Programming Language :: Python :: 3.5
Classifier: Programming Language :: Python :: 3.6
Classifier: Topic :: Software Development :: Libraries :: Python Modules
